Workbook

Sheet ACCUEIL
A1: 🚛 GESTION DE FLOTTE NC MALI
C4: 📊 TABLEAU DE BORD
C6: 🚚 FICHE CAMION 1
B7: 🚚 FICHE CAMION 2 | D7: 🚚 FICHE CAMION 3
B9: 🚚 FICHE CAMION 4 | D9: 🚚 FICHE CAMION 5
C11: 🏆 COMPARATIF PERFORMANCE

Sheet DASHBOARD
B1: 🚛 TABLEAU DE BORD - GESTION DE FLOTTE NC MALI
A2: 🏠 ACCUEIL | B2: TABLEAU DE BORD GÉNÉRAL | O2: Camion | P2: Revenu | Q2: Dépense | R2: Bénéfice
B3: 💰 REVENUS TOTAUX | E3: 💳 DÉPENSES TOTALES | H3: 📈 BÉNÉFICE NET | K3: 🚚 CAMIONS ACTIFS | O3: {=DASHBOARD!B12} -> 🚚 CAMION 1 | P3: {=DASHBOARD!D12} -> 3500000 | Q3: {=DASHBOARD!E12} -> 3751600 | R3: {=DASHBOARD!F12} -> -251600
A4: 📊 DASHBOARD | B4: =TEXT(D19,"# ##0")&" FCFA" -> 7 000 000 FCFA | E4: =TEXT(E19,"# ##0")&" FCFA" -> 8 254 850 FCFA | H4: =TEXT(F19,"# ##0")&" FCFA" -> -1 254 850 FCFA | K4: =COUNTIF(E12:E16,">0")&" / 5" -> 2 / 5 | O4: {=DASHBOARD!B13} -> 🚚 CAMION 2 | P4: {=DASHBOARD!D13} -> 3500000 | Q4: {=DASHBOARD!E13} -> 4503250 | R4: {=DASHBOARD!F13} -> -1003250
A5: 🏆 COMPARATIF | O5: {=DASHBOARD!B14} -> 🚚 CAMION 3 | P5: {=DASHBOARD!D14} -> 0 | Q5: {=DASHBOARD!E14} -> 0 | R5: {=DASHBOARD!F14} -> 0
A6: 🚚 CAMION 1
A7: 🚚 CAMION 2 | B7: Total des revenus générés | E7: Total des dépenses | H7: Profit total de la flotte | K7: Véhicules en opération
A8: 🚚 CAMION 3
A9: 🚚 CAMION 4 | B9: ="Marge moyenne: "&TEXT(G19/E19,"0.0%") -> Marge moyenne: 0.0% | E9: ="Bénéfice/Camion: "&TEXT(G19/COUNTIF(E12:E16,">0"),"# ##0")&" FCFA" -> Bénéfice/Camion: 0 FCFA | H9: ="Efficacité: "&TEXT(1-(F19/E19),"0%") -> Efficacité: 115%
A10: 🚚 CAMION 5
A11: 🚚 CAMION 5 | B11: 🚚 CAMION | C11: 👤 CHAUFFEUR | D11: 💰 REVENU (FCFA) | E11: 💳 DÉPENSE (FCFA) | F11: 📊 BÉNÉFICE (FCFA) | G11: 📈 MARGE %
B12: 🚚 CAMION 1 | C12: Moussa Kone 1 | D12: {='CAMION 1'!D44} -> 3500000 | E12: {='CAMION 1'!E44} -> 3751600 | F12: =D12-E12 -> -251600 | G12: =IF(D12>0,F12/D12,0) -> -0.071885714 | O12: Camion | P12: Revenu
B13: 🚚 CAMION 2 | C13: Moussa Kone 2 | D13: {='CAMION 2'!D45} -> 3500000 | E13: {='CAMION 2'!E45} -> 4503250 | F13: =D13-E13 -> -1003250 | G13: =IF(D13>0,F13/D13,0) -> -0.28664286 | O13: {=DASHBOARD!B12} -> 🚚 CAMION 1 | P13: {=DASHBOARD!D12} -> 3500000
B14: 🚚 CAMION 3 | D14: {='CAMION 3'!D45} -> 0 | E14: {='CAMION 3'!E45} -> 0 | F14: =D14-E14 -> 0 | G14: =IF(D14>0,F14/D14,0) -> 0 | O14: {=DASHBOARD!B13} -> 🚚 CAMION 2 | P14: {=DASHBOARD!D13} -> 3500000
B15: 🚚 CAMION 4 | D15: {='CAMION 4'!D45} -> 0 | E15: {='CAMION 4'!E45} -> 0 | F15: =D15-E15 -> 0 | G15: =IF(D15>0,F15/D15,0) -> 0 | O15: {=DASHBOARD!B14} -> 🚚 CAMION 3 | P15: {=DASHBOARD!D14} -> 0
B16: 🚚 CAMION 5 | D16: {='CAMION 5'!D45} -> 0 | E16: {='CAMION 5'!E45} -> 0 | F16: =D16-E16 -> 0 | G16: =IF(D16>0,F16/D16,0) -> 0
B19: 📊 TOTAL FLOTTE | D19: =SUM(D12:D16) -> 7000000 | E19: =SUM(E12:E16) -> 8254850 | F19: =SUM(F12:F16) -> -1254850 | G19: =IF(D19>0,F19/D19,0) -> -0.17926429
B22: Camion | C22: Marge %
B23: {=DASHBOARD!B12} -> 🚚 CAMION 1 | C23: {=DASHBOARD!G12} -> -0.071885714
B24: {=DASHBOARD!B13} -> 🚚 CAMION 2 | C24: {=DASHBOARD!G13} -> -0.28664286
B25: {=DASHBOARD!B14} -> 🚚 CAMION 3 | C25: {=DASHBOARD!G14} -> 0

Sheet SUPER-COMPARATIF
A2: 🏠 ACCUEIL | C2: 🏆 SUPER-COMPARATIF DE PERFORMANCE
A4: 📊 DASHBOARD
A5: 🏆 COMPARATIF | C5: PODIUM DE LA RENTABILITÉ
A6: 🚚 CAMION 1
A7: 🚚 CAMION 2 | D7: 🥇 1er RANG
A8: 🚚 CAMION 3 | C8: 🥈 2ème | D8: =INDEX(D12:D16,MATCH(LARGE(G12:G16,1),G12:G16,0)) -> CAMION 3 | E8: 🥉 3ème
A9: 🚚 CAMION 4 | C9: =INDEX(D12:D16,MATCH(LARGE(G12:G16,2),G12:G16,0)) -> CAMION 3 | E9: =INDEX(D12:D16,MATCH(LARGE(G12:G16,3),G12:G16,0)) -> CAMION 1
A10: 🚚 CAMION 5
A11: 🚚 CAMION 5
C12: RANG | D12: CAMION | E12: REVENU | F12: DÉPENSE | G12: BÉNÉFICE | H12: MARGE %
C13: 1 | D13: CAMION 1 | E13: ='CAMION 1'!D44 -> 3500000 | F13: ='CAMION 1'!E44 -> 3751600 | G13: =E13-F13 -> -251600 | H13: =G13/E13 -> -0.071885714
C14: 2 | D14: CAMION 2 | E14: ='CAMION 2'!D45 -> 3500000 | F14: ='CAMION 2'!E45 -> 4503250 | G14: =E14-F14 -> -1003250 | H14: =G14/E14 -> -0.28664286
C15: 3 | D15: CAMION 3 | E15: ='CAMION 3'!D45 -> 0 | F15: ='CAMION 3'!E45 -> 0 | G15: =E15-F15 -> 0 | H15: =G15/E15 -> #DIV/0!
C16: 4 | D16: CAMION 4 | E16: ='CAMION 4'!D45 -> 0 | F16: ='CAMION 4'!E45 -> 0 | G16: =E16-F16 -> 0 | H16: =IF(E16>0,G16/E16,0) -> 0
C17: 5 | D17: CAMION 5 | E17: ='CAMION 5'!D45 -> 0 | F17: ='CAMION 5'!E45 -> 0 | G17: =E17-F17 -> 0 | H17: =IF(E17>0,G17/E17,0) -> 0

Sheet CAMION 1
B1: 🚚 Renauld Blanc : Moussa Kone 1
A2: 🏠 ACCUEIL | B2: SUIVI : CAMION 1
A4: 📊 DASHBOARD
A5: 🏆 COMPARATIF
A6: 🚚 CAMION 1
A7: 🚚 CAMION 2
A8: 🚚 CAMION 3
A9: 🚚 CAMION 4 | C9: DATE | D9: CATÉGORIE | E9: DESCRIPTION | F9: REVENU | G9: DÉPENSE | H9: PAIEMENT
A10: 🚚 CAMION 5 | C10: 46077 | D10: ⛽ CARBURANT | E10: 1100 L | G10: 737000 | H10: Espèce
A11: 🚚 CAMION 5 | C11: 46077 | D11: 🛣️ FRAIS DE ROUTE | E11: Aller-Retour | G11: 360000 | H11: Espèce
C12: 46077 | D12: ⛽ CARBURANT | E12: 400 L Suplémentaire | G12: 268000 | H12: Espèce
C13: 46077 | D13: ⚙️ AUTRES | E13: Douane pour caroserie pas dans les normes | G13: 204000 | H13: Espèce
C14: 46077 | D14: 🔧 REPARATION | E14: 4 Pneus *110 000 | G14: 457600 | H14: Espèce
C15: 46077 | D15: ⚙️ AUTRES | E15: Révenu | F15: 3500000 | H15: Espèce
C16: 46093 | D16: 💰 SALAIRE | E16: 1mois | G16: 100000 | H16: Espèce
C17: 46093 | E17: 1Voyages | G17: 50000 | H17: Espèce
C18: 46093 | D18: 🔧EPARATION | E18: 1 Pneu | G18: 110000 | H18: Espèce
C19: 46093 | D19: ⚙️ AUTRES | E19: Eau bloutc | G19: 50000 | H19: Espèce
C20: 46093 | D20: 🛠️ ENTRETIEN | E20: Air | G20: 3000 | H20: Espèce
C21: 46093 | D21: ⛽ CARBURANT | E21: 1100 L | G21: 737000 | H21: Espèce
C22: 46093 | D22: 🛣️ FRAIS DE ROUTE | E22: Aller-Retour | G22: 360000 | H22: Espèce
C23: 46108 | D23: ⚙️ AUTRES | E23: Vignette | G23: 290000 | H23: Espèce
C24: 27/0/2026 | D24: ⚙️ AUTRES | E24: Ration | G24: 25000 | H24: Espèce
C44: TOTAL | D44: =SUM(F10:F43) -> 3500000 | E44: =SUM(G10:G43) -> 3751600
D45: REVENUE | E45: DEPENSE

Sheet CAMION 2
B1: 🚚 Renauld Rouge : Moussa Kone 2
A2: 🏠 ACCUEIL | B2: SUIVI : CAMION 2
A4: 📊 DASHBOARD
A5: 🏆 COMPARATIF
A6: 🚚 CAMION 1
A7: 🚚 CAMION 2
A8: 🚚 CAMION 3
A9: 🚚 CAMION 4 | C9: DATE | D9: CATÉGORIE | E9: DESCRIPTION | F9: REVENU | G9: DÉPENSE | H9: PAIEMENT
A10: 🚚 CAMION 5 | C10: 46077 | D10: ⛽ CARBURANT | E10: 1300 L | G10: 871000 | H10: Espèce
A11: 🚚 CAMION 5 | C11: 46077 | D11: 🛣️ FRAIS DE ROUTE | E11: Aller-Retour | G11: 360000 | H11: Espèce
C12: 46077 | D12: 🔧 REPARATION | E12: Frais de réparation camion | G12: 390250 | H12: Espèce
C13: 46077 | D13: ⛽ CARBURANT | E13: 200 L Suplementaire | G13: 134000 | H13: Espèce
C14: 46077 | D14: ⚙️ AUTRES | E14: Arrangement Police | G14: 10000 | H14: Espèce
C15: 46080 | D15: ⚙️ AUTRES | E15: Revenu | F15: 3500000 | H15: Espèce
C16: 46080 | D16: ⛽ CARBURANT | E16: 1300 L | G16: 871000 | H16: Espèce
C17: 46080 | D17: 🛣️ FRAIS DE ROUTE | E17: Aller-Retour | G17: 360000 | H17: Espèce
C18: 46080 | D18: 💰 SALAIRE | E18: 2 mois de Salaire | G18: 200000 | H18: Espèce
C19: 46080 | D19: 🏅 PRIME | E19: 1 Voyage | G19: 50000 | H19: Espèce
C20: 46108 | D20: 💰 SALAIRE | E20: 1 mois salaire | G20: 100000 | H20: Espèce
C21: 46108 | D21: 🏅 PRIME | E21: 1 voyage | G21: 50000 | H21: Espèce
C22: 46108 | D22: 💰 SALAIRE | E22: 1 mois de salaire qui était passé | G22: 100000 | H22: Espèce
C23: 46108 | D23: 🏅 PRIME | E23: 1voyage | G23: 50000 | H23: Espèce
C24: 46108 | D24: 🔧 REPARATION | E24: Jante | G24: 35000 | H24: Espèce
C25: 46108 | D25: 🛠️ ENTRETIEN | E25: Huile Moteur | G25: 130000 | H25: Espèce
C26: 46108 | D26: 🛠️ ENTRETIEN | E26: Climatisation | G26: 15000 | H26: Espèce
C27: 46108 | D27: ⚙️ AUTRES | E27: vignette | G27: 290000 | H27: Espèce
... C30: 46108 | D30: 🔧 REPARATION | E30: Montage Pneu | G30: 3000 | H30: Espèce
C45: TOTAL | D45: =SUM(F10:F44) -> 3500000 | E45: =SUM(G10:G44) -> 4503250
D46: REVENUE | E46: DEPENSE

Sheet CAMION 3
B1: 🚚 CAMION 3
A2: 🏠 ACCUEIL | B2: SUIVI : CAMION 3
A4: 📊 DASHBOARD
A5: 🏆 COMPARATIF
A6: 🚚 CAMION 1
A7: 🚚 CAMION 2
A8: 🚚 CAMION 3
A9: 🚚 CAMION 4 | C9: DATE | D9: CATÉGORIE | E9: DESCRIPTION | F9: REVENU | G9: DÉPENSE | H9: PAIEMENT
A10: 🚚 CAMION 5
A11: 🚚 CAMION 5
C45: TOTAL | D45: =SUM(F10:F44) -> 0 | E45: =SUM(G10:G44) -> 0

Sheet CAMION 4
B1: 🚚 CAMION 4
A2: 🏠 ACCUEIL | C2: SUIVI : CAMION 4
A4: 📊 DASHBOARD
A5: 🏆 COMPARATIF
A6: 🚚 CAMION 1
A7: 🚚 CAMION 2
A8: 🚚 CAMION 3
A9: 🚚 CAMION 4 | C9: DATE | D9: CATÉGORIE | E9: DESCRIPTION | F9: REVENU | G9: DÉPENSE | H9: PAIEMENT
A10: 🚚 CAMION 5
A11: 🚚 CAMION 5
C45: TOTAL | D45: =SUM(F10:F44) -> 0 | E45: =SUM(G10:G44) -> 0

Sheet CAMION 5
B1: 🚚 CAMION 5
A2: 🏠 ACCUEIL | C2: SUIVI : CAMION 5
A4: 📊 DASHBOARD
A5: 🏆 COMPARATIF
A6: 🚚 CAMION 1
A7: 🚚 CAMION 2
A8: 🚚 CAMION 3
A9: 🚚 CAMION 4 | C9: DATE | D9: CATÉGORIE | E9: DESCRIPTION | F9: REVENU | G9: DÉPENSE | H9: PAIEMENT
A10: 🚚 CAMION 5
A11: 🚚 CAMION 5
C45: TOTAL | D45: =SUM(F10:F44) -> 0 | E45: =SUM(G10:G44) -> 0
